stonecharioteer/__init__.py
stonecharioteer/constants.py
stonecharioteer/logger.py
stonecharioteer/qtile/__init__.py
stonecharioteer/qtile/groups.py
stonecharioteer/qtile/inputs.py
stonecharioteer/qtile/keymaps.py
stonecharioteer/qtile/layouts.py
stonecharioteer/qtile/panels.py
stonecharioteer/qtile/screens.py
stonecharioteer/utils/displays.py
stonecharioteer-0.7.7.dist-info/METADATA
stonecharioteer-0.7.7.dist-info/WHEEL
stonecharioteer-0.7.7.dist-info/RECORD
