Metadata-Version: 2.1
Name: stonecharioteer
Version: 0.7.7
Summary: My personal utils and configs, managed via python library
Author: Vinay Keerthi
Author-email: 11478411+stonecharioteer@users.noreply.github.com
Requires-Python: >=3.9,<4.0
Classifier: Programming Language :: Python :: 3
Classifier: Programming Language :: Python :: 3.9
Classifier: Programming Language :: Python :: 3.10
Classifier: Programming Language :: Python :: 3.11
Requires-Dist: mypy (>=0.910,<0.911)
Requires-Dist: psutil (>=5.8.0,<6.0.0)
Requires-Dist: python-xlib (>=0.31,<0.32)
Requires-Dist: qtile (>=0.18.1)
Requires-Dist: requests (>=2.26.0,<3.0.0)
Requires-Dist: rich (>=10.12.0,<11.0.0)
Requires-Dist: toml (>=0.10.2,<0.11.0)
Requires-Dist: typeguard (>=2.13.3,<3.0.0)
Requires-Dist: types-toml (>=0.10.1,<0.11.0)
